Metadata-Version: 2.1
Name: resszo
Version: 0.1
Summary: TYPE YOUR DESCRIPTION HERE
Home-page: https://github.com/user/resszo
Author: YOUR NAME
Author-email: your.email@domain.com
License: MIT
Project-URL: Documentation, https://github.com/pypa/resszo/
Project-URL: Funding, https://donate.pypi.org
Project-URL: Say Thanks!, http://saythanks.io/to/example
Project-URL: Source, https://github.com/pypa/resszo/
Project-URL: Tracker, https://github.com/pypa/resszo/issues
Keywords: SOME,MEANINGFULL,KEYWORDS
Classifier: Development Status :: 3 - Alpha
Classifier: Intended Audience :: Developers
Classifier: Topic :: Software Development :: Build Tools
Classifier: License :: OSI Approved :: MIT License
Classifier: Programming Language :: Python :: 3
Classifier: Programming Language :: Python :: 3.4
Classifier: Programming Language :: Python :: 3.5
Classifier: Programming Language :: Python :: 3.6
License-File: LICENSE
Requires-Dist: validators
Requires-Dist: beautifulsoup4
Requires-Dist: discorudo
